MANIFEST.in
README.md
requirements.txt
setup.py
foto2/__init__.py
foto2/exceptions.py
foto2/foto.py
foto2/foto_tools.py
foto2.egg-info/PKG-INFO
foto2.egg-info/SOURCES.txt
foto2.egg-info/dependency_links.txt
foto2.egg-info/not-zip-safe
foto2.egg-info/requires.txt
foto2.egg-info/top_level.txt