Metadata-Version: 2.1
Name: foto2
Version: 0.1.3
Summary: Fourier Transform Textural Ordination
Home-page: http://github.com/benjaminpillot/foto
Author: Benjamin Pillot
Author-email: benjaminpillot@riseup.net
License: GNU GPL v3.0
Platform: UNKNOWN
Requires-Python: >=3
